.gitignore
AUTHORS
COPYING
Makefile
README
pylintrc
setup.cfg
setup.py
bin/dt-lint
bin/dt-plot
decotengu/__init__.py
decotengu/const.py
decotengu/conveyor.py
decotengu/engine.py
decotengu/error.py
decotengu/flow.py
decotengu/ft.py
decotengu/model.py
decotengu/output.py
decotengu.egg-info/PKG-INFO
decotengu.egg-info/SOURCES.txt
decotengu.egg-info/dependency_links.txt
decotengu.egg-info/top_level.txt
decotengu/alt/__init__.py
decotengu/alt/bisect.py
decotengu/alt/decimal.py
decotengu/alt/naive.py
decotengu/alt/tab.py
decotengu/tests/__init__.py
decotengu/tests/test_conveyor.py
decotengu/tests/test_engine.py
decotengu/tests/test_flow.py
decotengu/tests/test_ft.py
decotengu/tests/test_model.py
decotengu/tests/test_output.py
decotengu/tests/tools.py
decotengu/tests/alt/__init__.py
decotengu/tests/alt/test_bisect.py
decotengu/tests/alt/test_decimal.py
decotengu/tests/alt/test_naive.py
decotengu/tests/alt/test_tab.py
decotengu/tests/integration/__init__.py
decotengu/tests/integration/test_decimal.py
decotengu/tests/integration/test_decostepper.py
decotengu/tests/integration/test_engine.py
decotengu/tests/integration/test_tab.py
doc/algo.rst
doc/alt.rst
doc/api.rst
doc/changelog.rst
doc/cmd.rst
doc/conf.py
doc/decolessons.pdf
doc/deepstops.pdf
doc/design.rst
doc/dive-cmp.png
doc/dive.png
doc/equations.ipynb
doc/gfdeco.f
doc/index.rst
doc/info.rst
doc/model.rst
doc/mvalues.pdf
doc/tissue-pressure-plot.png
doc/usage.rst
doc/static/decotengu.css
scripts/dt-mega-walk
scripts/dt-ndl-check
scripts/dt-perf
scripts/test_random.py