Metadata-Version: 1.1
Name: decotengu
Version: 0.14.0
Summary: DecoTengu - dive decompression library
Home-page: http://wrobell.it-zone.org/decotengu/
Author: Artur Wroblewski
Author-email: wrobell@pld-linux.org
License: GPL
Keywords: diving dive decompression
Platform: UNKNOWN
Classifier: License :: OSI Approved :: GNU General Public License v3 or later (GPLv3+)
Classifier: Programming Language :: Python :: 3
Classifier: Development Status :: 4 - Beta
